{"posts": {"post": [{"stop_lat": "40.024206", "stop_name": "Frankford Transportation Center", "stop_lon": "-75.077997", "stop_id": "21211"}, {"stop_lat": "40.013225", "stop_name": "Bridge St And Torresdale Ave", "stop_lon": "-75.070557", "stop_id": "487"}, {"stop_lat": "40.038163", "stop_name": "Bustleton Ave And Magee Ave", "stop_lon": "-75.068032", "stop_id": "505"}, {"stop_lat": "40.047396", "stop_name": "Tabor Rd And Levick St", "stop_lon": "-75.091978", "stop_id": "507"}, {"stop_lat": "40.034506", "stop_name": "Rising Sun Ave And Olney Ave", "stop_lon": "-75.115424", "stop_id": "15896"}, {"stop_lat": "40.037583", "stop_name": "One And Onley Square", "stop_lon": "-75.118047", "stop_id": "27715"}, {"stop_lat": "40.038599", "stop_name": "Olney Transportation Center", "stop_lon": "-75.142456", "stop_id": "381"}, {"stop_lat": "40.045385", "stop_name": "Chew Ave And Chelten Ave", "stop_lon": "-75.165121", "stop_id": "21228"}, {"stop_lat": "40.029700", "stop_name": "Chelten Ave And Morris St", "stop_lon": "-75.181020", "stop_id": "496"}]}}