{"posts": {"post": [{"stop_lat": "39.979092", "stop_name": "Richmond St And Cambria St", "stop_lon": "-75.109157", "stop_id": "20596"}, {"stop_lat": "39.991335", "stop_name": "Kensington Ave And Somerset St", "stop_lon": "-75.122454", "stop_id": "21262"}, {"stop_lat": "39.992412", "stop_name": "6th St And Lehigh Ave", "stop_lon": "-75.142272", "stop_id": "20597"}, {"stop_lat": "39.993926", "stop_name": "Broad St And Lehigh Ave", "stop_lon": "-75.154417", "stop_id": "20547"}, {"stop_lat": "39.995623", "stop_name": "22nd St And Lehigh Ave", "stop_lon": "-75.167455", "stop_id": "20598"}, {"stop_lat": "39.991992", "stop_name": "33rd And Dauphin Sts", "stop_lon": "-75.186019", "stop_id": "644"}]}}